ghopenid/__init__.py
ghopenid/py.typed
ghopenid/warning.py
ghopenid/connect/__init__.py
ghopenid/connect/discovery.py
ghopenid/connect/grant_types.py
ghopenid/connect/repository.py
ghopenid/connect/request.py
ghopenid/connect/validator.py
ghopenid-0.6.0.dist-info/LICENSE
ghopenid-0.6.0.dist-info/METADATA
ghopenid-0.6.0.dist-info/WHEEL
ghopenid-0.6.0.dist-info/top_level.txt
ghopenid-0.6.0.dist-info/RECORD
